onec_py_rac/__init__.py
onec_py_rac/interac.py
onec_py_rac/ras_1c.py
onec_py_rac-0.1.2.dist-info/LICENSE
onec_py_rac-0.1.2.dist-info/WHEEL
onec_py_rac-0.1.2.dist-info/METADATA
onec_py_rac-0.1.2.dist-info/RECORD
