Metadata-Version: 2.1
Name: onec_py_rac
Version: 0.1.2
Summary: Interact with RAS server 1C Enterpise platform
Author-email: Tsys Maxim <catchier@gmail.com>
Classifier: License :: OSI Approved :: GNU General Public License v3 or later (GPLv3+)
Project-URL: Home, https://gitflic.ru/project/catchier/onec_py_rac
